{"title": "Asociaci\u00f3n Galega de linfedema, lipedema, insuficiencia venosa cr\u00f3nica y otras patolog\u00edas", "author": "Publicado por Asociaci\u00f3n Galega de Linfedema", "url": "http://blog.linfedemagalicia.com/", "hostname": "linfedemagalicia.com", "description": "(blog) Asociaci\u00f3n Galega de linfedema, lipedema, insuficiencia venosa cr\u00f3nica y otras patolog\u00edas", "sitename": "blog.linfedemagalicia.com", "date": "2023-09-15", "cleaned_text": "Septiembre es el Mes de la Concienciaci\u00f3n sobre las Enfermedades Vasculares. Las enfermedades venosas afectan aproximadamente el 40-50% de la poblaci\u00f3n, mucho m\u00e1s que las cardiopat\u00edas y los accidentes cerebrovasculares. Existe poca informaci\u00f3n sobre las enfermedades vasculares, a pesar de que todas las partes del cuerpo podr\u00edan verse afectadas ya que la sangre y la linfa fluye por todo nuestro cuerpo. El sistema circulatorio sangu\u00edneo est\u00e1 formado por venas superficiales y profundas, que transportan la sangre pobre en ox\u00edgeno de vuelta al coraz\u00f3n para que pueda re oxigenarse antes de volver a circular por el organismo. Las venas son una parte importante del sistema circulatorio, y es importante tratar las enfermedades venosas cuando se detectan las se\u00f1ales de alarma, ya que pueden afectar negativamente a la circulaci\u00f3n. La mayor\u00eda de la gente no es consciente de los problemas que pueden causar las venas. La enfermedad venosa puede asociarse a una sensaci\u00f3n de plenitud y presi\u00f3n, y posiblemente a dolor y fatiga en la parte inferior de la pierna a medida que avanza el d\u00eda. La enfermedad venosa puede causar hinchaz\u00f3n (edema) y cambios en la piel en el futuro. A veces, los problemas venosos requieren intervenciones m\u00e9dicas como medicaci\u00f3n o un tratamiento m\u00e1s intensivo para restablecer la salud y funcionalidad de las venas, y el plan de tratamiento depende de la enfermedad venosa concreta y de su gravedad. Las enfermedades vasculares pueden provocar complicaciones si no se tratan. Algunas pueden requerir tratamiento inmediato, mientras que otras pueden empeorar lentamente con el tiempo. En cualquier caso, cualquier enfermedad que afecte a la salud y el funcionamiento de las venas o las arterias debe tomarse en serio. Algunos ejemplos de enfermedades vasculares son: - Enfermedades arteriales, como la arteriopat\u00eda perif\u00e9rica, la arteriopat\u00eda renal, el s\u00edndrome de atrapamiento popl\u00edteo la arteriopat\u00eda vasculares, \u00falceras venosas, tromboflebitis superficial e insuficiencia venosa cr\u00f3nica. - Trastornos de la coagulaci\u00f3n sangu\u00ednea, incluida la embolia pulmonar y la trombosis venosa profunda (TVP). - Aneurisma a\u00f3rtico - Linfedema Como mejorar los problemas venosos - Ejercicio regular - H\u00e1bitos alimentarios saludables - Control del colesterol \"malo\" - Dejar de fumar - Limitar el consumo de alcohol - Reducir el estr\u00e9s - Limitar la permanencia sentada o de pie durante largos periodos de tiempo - Utilizar medias de compresi\u00f3n. Ayude a compartir la informaci\u00f3n y a concienciar sobre las enfermedades vasculares durante todo el mes de septiembre REFERENCIAS (Pinche sobre los textos para le\u00e9r los art\u00edculos cient\u00edficos) "}