{"title": "Vacuna Antineumoc\u00f3ccica", "author": null, "url": null, "hostname": null, "description": "Grav is an easy to use, yet powerful, open source flat-file CMS", "sitename": null, "date": "2020-10-01", "cleaned_text": "VACUNA ANTINEUMOC\u00d3CCICA En 1944, se utiliz\u00f3 la primera vacuna. En 1977, se autoriz\u00f3 en EE.UU. una presentaci\u00f3n con 14 serotipos. A partir de 1983, esta vacuna polivalente fue elaborada con ant\u00edgenos polisac\u00e1ridos capsulares purificados, de 23 serotipos, responsables del 85 a 90% de las infecciones neumoc\u00f3ccicas. Provee adem\u00e1s, protecci\u00f3n cruzada con otros serotipos. Luego surgi\u00f3 una vacuna conjugada de 7 serotipos y actualmente existen otras presentaciones pedi\u00e1tricas, de 10 y 13 serotipos. Tipos de Vacunas e Indicaciones Existen cuatro tipos de vacunas polivalentes: - 23 serotipos. - 7 serotipos. - 10 serotipos. - 13 serotipos. Vacuna de 23 serotipos - VPN23 (polisac\u00e1rida, no conjugada): Contiene, seg\u00fan la nomenclatura danesa, los siguientes serotipos: 1, 2, 3, 4, 5, 6B, 7F, 8, 22F, 23F y 33F. Por inmunidad cruzada, cubre un espectro de 27 serotipos, por lo que protege contra el 92% de las formas invasivas (en Argentina, el 82% de los serotipos aislados por vigilancia epidemiol\u00f3gica, est\u00e1n representados en esta vacuna). Se puede utilizar desde los 2 a\u00f1os. Por debajo de esta edad, la respuesta es pobre, por lo que su aplicaci\u00f3n es limitada en el grupo et\u00e1reo que presenta el 80% de las infecciones neumoc\u00f3ccicas graves. Tiene una duraci\u00f3n m\u00ednima de 5 a\u00f1os (en inmunocomprometidos baja a tres). Se ha observado disminuci\u00f3n de bacteriemias en aspl\u00e9nicos y esplenectomizados. En mayores de 65 a\u00f1os tiene un alto \u00edndice de efectividad. No elimina la portaci\u00f3n nasofar\u00edngea (no tiene efecto reba\u00f1o). Las indicaciones son: - Mayores de 65 a\u00f1os. - Pacientes con enfermedad cardiopulmonar cr\u00f3nica, diabetes, insuficiencia renal cr\u00f3nica, sindrome nefr\u00f3tico, cirrosis, alcoholismo, aspl\u00e9nicos funcionales o quir\u00fargicos, drepanocitosis, mieloma m\u00faltiple, f\u00edstulas de l\u00edquido cefalorraqu\u00eddeo, trasplante de m\u00e9dula \u00f3sea, Hodgkin, otitis cr\u00f3nica recidivante. - Infectados HIV. - Inmunocomprometidos o inmunosupresor nefr\u00f3tico; quimioterapia o tratamiento prolongado con corticoides). - Trasplantes de \u00f3rgano s\u00f3lido. - Residentes de geri\u00e1tricos y asilos. - Personal de salud en contacto con grupos de alto riesgo. El Comit\u00e9 Asesor de Pr\u00e1cticas de Inmunizaci\u00f3n de los EE.UU.(ACIP), hace esta recomendaci\u00f3n resumida: - Mayores de 65 a\u00f1os. - Inmunocompetentes desde los 2 a\u00f1os con riesgo de enfermedad o muerte por patolog\u00edas cr\u00f3nicas. - Personas desde los 2 a\u00f1os con asplenia funcional o anat\u00f3mica. - Personas desde los 2 a\u00f1os viviendo en un medio ambiente con riesgo de enfermedad alto. - Inmunocomprometidos mayores de 2 a\u00f1os. La respuesta de anticuerpos se da a partir de pasados 14 d\u00edas, por lo tanto en esplenectom\u00edas programadas, terapia antineopl\u00e1sica o transplante de m\u00e9dula \u00f3sea, se debe inmunizar 2 a 3 semanas antes. Se aplica por v\u00eda intramuscular, en el brazo (deltoides). Puede ser aplicada en forma simult\u00e1nea con otras vacunas, en sitios diferentes. Esta vacuna no ha sido evaluada en embarazadas, por lo tanto no se aconseja su aplicaci\u00f3n rutinaria. Revacunaci\u00f3n: Se har\u00e1 s\u00f3lo una revacunaci\u00f3n a pacientes con alto riesgo de padecer infecci\u00f3n invasiva neumoc\u00f3ccica severa (asplenia funcional o anat\u00f3mica; insuficiencia renal cr\u00f3nica, s\u00edndrome nefr\u00f3tico, infecci\u00f3n HIV, transplante, leucemia, linfoma, mieloma m\u00faltiple, otros c\u00e1nceres y tratamiento inmunosupresor). No est\u00e1 indicado en enfermedad cr\u00f3nica card\u00edaca o pulmonar, hep\u00e1tica, diabetes mellitus, alcoholismo o f\u00edstula de LCR o inmunocompetentes, salvo que hubieran recibido una dosis antes de los 65 a\u00f1os. En ni\u00f1os se realizar\u00e1 la revacunaci\u00f3n, pasados 3 a\u00f1os de la primera, en menores de 10 a\u00f1os de edad; y luego de 5 a\u00f1os, en ni\u00f1os de m\u00e1s de 10 a\u00f1os de edad. Las personas de 65 a\u00f1os o m\u00e1s, se revacunar\u00e1n luego de 5 a\u00f1os de la primera dosis, si \u00e9sta fue recibida siendo menor de esa edad. . No se deben administrar, en total, m\u00e1s de 2 dosis de VPN-23 antes de los 65 a\u00f1os de edad. Nota: La vacuna de marca Pneumovax \u00ae, NO debe administrarse simult\u00e1neamente con Zostavax\u00ae (vacuna contra el herpes z\u00f3ster), ya que disminuye la inmunogenicidad de esta \u00faltima. Vacuna de 7 serotipos (conjugada): Fue la primera vacuna antineumoc\u00f3ccica conjugada heptavalente, efectiva en ni\u00f1os menores de 2 a\u00f1os. Este inmunizante inclu\u00eda los serotipos 4, 6B, 9V, 14, 18C, 19F y 23F; conjugados con una prote\u00edna dift\u00e9rica no t\u00f3xica (CRM197) que aumenta su inmunogenicidad y fosfato de aluminio como coadyuvante. En menores de 6 a\u00f1os, provee una protecci\u00f3n cercana al 90% para infecci\u00f3n neumoc\u00f3cica causante de bacteriemia, siendo las cifras de 21% y 82%, en casos de otitis media y meningitis respectivamente, en los EE.UU. En ese pa\u00eds, antes de la vacunaci\u00f3n, esta bacteria provocaba 16.000 casos graves y 1.400 meningitis en menores de 5 a\u00f1os. A pesar de que haber sido recomendada por la Academia Americana de Pediatr\u00eda, su elevado costo gener\u00f3 reparos y controversias en algunos sectores. Hoy ya ha sido reemplazada por sus sucesoras. Vacuna de 10 serotipos - VCN-10 (conjugada): Vacuna adsorbida conjugada con prote\u00edna de Haemophilus influenzae no tipificable (HiNT). Efectiva desde las 6 semanas de vida hasta los 2 a\u00f1os. Agrega a la anterior, los serotipos 1, 5 y 7F y tendr\u00eda reacci\u00f3n cruzada con el 6A y el 19A. La inmunogenicidad es similar a la heptavalente: protege contra infecciones por neumococo (serotipos de la vacuna), incluidas las invasivas. Adem\u00e1s obtendr\u00eda una respuesta importante contra la otitis media provocada por neumococos y HiNT. Vacuna de 13 serotipos - VCN13 (conjugada): \u00c9sta suma a la anterior, los serotipos 3, 6A y 19A y utiliza la misma prote\u00edna que la de 7 serotipos. Las dos \u00faltimas vacunas cubren un espectro importante de los serotipos prevalentes en la Argentina (la 13 valente, de uso oficial, abarca el 90% de los serotipos en menores de 2 a\u00f1os). Las bases para el uso racional de las vacunas antineumoc\u00f3ccicas son: - Prevenci\u00f3n de la enfermedad invasiva y no invasiva. - Reducci\u00f3n de portadores. - Reducci\u00f3n de la transmisi\u00f3n. - Reducci\u00f3n de la resistencia antibi\u00f3tica. - Induce la respuesta de memoria inmunol\u00f3gica. Nota: Las vacunas conjugadas provocan una respuesta adecuada en los ni\u00f1os menores de 2 a\u00f1os, generando inmunidad individual y, al disminuir la portaci\u00f3n nasofar\u00edngea, confieren inmunidad de reba\u00f1o (efecto indirecto de inmunidad colectiva). Nota: En junio de 2021, la FDA aprob\u00f3 en forma acelerada, la Prevnar 20, que agrega 7 serotipos m\u00e1s a la Prevnar 13 (8, 10A, 11A, 12F, 15B, 22F y 33F). Destinada a mayores de 18 a\u00f1os, a\u00fan se espera la especificaci\u00f3n de los CDC, para su indicaci\u00f3n precisa. Contraindicaciones Reacci\u00f3n al\u00e9rgica severa a alguno de los componentes de la vacuna. En la de 23 serotipos, no debe revacunarse antes de pasados 3 a 5 a\u00f1os de la aplicaci\u00f3n anterior, seg\u00fan edad y patolog\u00eda. Efectos Colaterales Eritema, inflamaci\u00f3n y dolor en el sitio de inoculaci\u00f3n. - En la de 23 serotipos, se observan hasta en un 40% de los inoculados y son leves y transitorios. Las reacciones severas no alcanzan al 1%, pero aumentan si se revacuna antes de los 5 a\u00f1os. Esta repetici\u00f3n de la vacuna s\u00f3lo est\u00e1 indicada en pacientes de alto riesgo. - En las conjugadas, las reacciones generales son m\u00e1s evidentes al hacerse en forma simult\u00e1nea con las vacunas DPT y antihaemophilus, aunque son raras las complicaciones severas. En prematuros de menos de 28 semanas o lactantes con antecedentes de inmadurez pulmonar, deber\u00e1 evaluarse el riesgo de apnea y/o monitorear las 48-72 hs despu\u00e9s de la inmunizaci\u00f3n. En la 13-valente, en los adultos, pueden presentarse cefaleas, cansancio, escalofr\u00edos, rash, diarrea, artralgias o mialgias. Situaci\u00f3n en Am\u00e9rica En febrero del '96, se reunieron en La Habana, Cuba, representantes de cinco laboratorios centro y sudamericanos: Instituto Finlay (Cuba), Butantan (Brasil), Bio-Manguinhos/FIOCRUZ (Brasil), Malbr\u00e1n (Argentina) y el Instituto de Higiene (Uruguay). La coordinaci\u00f3n estuvo a cargo del SIREVA y SVI (Programa Especial para Vacunas e Inmunizaci\u00f3n) de la OPS. Estos \u00faltimos trabajan en colaboraci\u00f3n con el LCDC de Ottawa y el Laboratorio de Referencia de Estreptococos de la Universidad de Alberta; ambos en Canad\u00e1. El objetivo de esta reuni\u00f3n fue implementar el desarrollo de tecnolog\u00edas de producci\u00f3n y purificaci\u00f3n de polisac\u00e1ridos de serotipos de Sp, prevalentes en la Regi\u00f3n; para lograr una vacuna m\u00e1s adecuada a las necesidades de la misma. Se destac\u00f3 la importancia de la cooperaci\u00f3n para lograr una vacuna conjugada, que sea efectiva desde antes de los 2 a\u00f1os, ya que sus costos son muy altos. Calendario Nacional de Vacunaci\u00f3n (Argentina) Desde enero de 2012, la vacuna conjugada 13-valente fue incorporada al Calendario Nacional (gratuito y obligatorio), en un esquema de dos dosis y un refuerzo, para menores de 1 a\u00f1o (2, 4 y 12 ms). Los que iniciaren el esquema despu\u00e9s del a\u00f1o, se aplican dos dosis con un intervalo m\u00ednimo de 2 meses. Los RN pret\u00e9rmino inician su vacunaci\u00f3n superados los 1.800g. Nota 1: Cualquier esquema debe respetar un m\u00ednimo de 8 semanas entre dosis. Puede aplicarse simult\u00e1neamente con otras vacunas. Las inmunoglobulinas no influyen en la respuesta inmunol\u00f3gica. Nota 2: En mayores de 50 a\u00f1os, se ha encontrado que la respuesta de anticuerpos a la vacuna 13-valente se redujo al ser administrada simult\u00e1neamente con la vacuna antigripal inactivada; situaci\u00f3n que no se observ\u00f3 en la administraci\u00f3n por separado. AMPLIACI\u00d3N DE LAS INDICACIONES - 2015 Mayores de 18 a\u00f1os con ciertas enfermedades Infecci\u00f3n por VIH - Inmunodeficiencias cong\u00e9nitas o adquiridas o farmacol\u00f3gicas - Sindrome nefr\u00f3tico - Insuficiencia renal cr\u00f3nica - Leucemia - Linfoma y Enfermedad de Hodgkin - Neoplasias - Trasplante de \u00f3rgano s\u00f3lido - Mieloma m\u00faltiple - Asplenia funcional o anat\u00f3mica - Anemia de falciformes - Implante coclear - F\u00edstula de LCR. Esquema: - 1 dosis de VCN13 - 1a dosis de VPN23 con un m\u00ednimo de espera de 8 semanas con la anterior - 2a dosis (refuerzo) de VPN23 a los 5 a\u00f1os de la primera. Debe hacerse otro refuerzo a los 65 a\u00f1os (si la dosis anterior fue aplicada antes de los 60 a\u00f1os y tambi\u00e9n con un m\u00ednimo de 5 a\u00f1os de intervalo) - En las esplenectom\u00edas (extracci\u00f3n del bazo) programadas, se administra 15 d\u00edas antes. Mayores de 18 a\u00f1os con las siguientes condiciones Cardiopat\u00eda cr\u00f3nica - Enfermedad pulmonar cr\u00f3nica - Diabetes Mellitus - Alcoholismo - Enfermedad hep\u00e1tica cr\u00f3nica - Tabaquismo Esquema: a) Entre 18 y 64 a\u00f1os: - 1 dosis de VPN23 en cualquier momento - 1 dosis de refuerzo a los 65 a\u00f1os (siempre con 5 a\u00f1os de diferencia con la anterior) b) Mayores de 65 a\u00f1os: - 1 dosis de VPN23 (lo m\u00e1s temprano posible) Mayores de 65 a\u00f1os (sanos) - 1 dosis de VPN23 (lo m\u00e1s temprano posible) Ver las nuevas [Recomendaciones del Comit\u00e9 Asesor sobre Pr\u00e1cticas de Inmunizaci\u00f3n (ACIP)](https://hosting.cs.uns.edu.ar/~inf-vacunas/enfermedades-y-vacunas/a-neumococo/novedades/nuevas-recomendaciones-del-acip) de los Estados Unidos (Junio 2019). "}