{"title": "Desconecta", "author": null, "url": "https://www.elle.com/es/living/viajes/news/g480761/spas-exclusivos/", "hostname": "elle.com", "description": "Una ruta, de norte a sur, por los mejores spas y los salones m\u00e1s exclusivos.", "sitename": "ELLE", "date": "2012-08-14", "cleaned_text": "Desconecta Te proponemos un 'beauty tour' por los mejores salones y 'spas' de nuestro pa\u00eds, donde podr\u00e1s recibir los cuidados m\u00e1s solicitados por las 'celebrities'. Villa Padierna \u00bfQuieres darte un capricho? No te pierdas los tratamientos del Beauty Club de Marta Boira. Ponte en manos de sus profesionales y disfruta de sus protocolos high tech con marcas premium como Sisley o Evidens, te dejar\u00e1n como nueva. Urbanizaci\u00f3n Flamingos Golf, Marbella. Tel. 952 88 91 50, Hotel Hesperia Rel\u00e1jate y cu\u00eddate a partes iguales en este espectacular resort. Empieza el d\u00eda con sus famosos desayunos detox, a base de frutas de temporada, y no pierdas sus fant\u00e1sticas vistas al mar mientras te das un ba\u00f1o en sus piscinas tropicales. La crema 'Soin Perfection Corps Anti-\u00c2ge' de Orlane', 87 \u20ac. Urb. Cortijo Viejo, Puerto Calero, Lanzarote. Tel. 828 080 800. Slow Life House Un centro que mira por tu belleza y por tu bienestar interior. Prueba el Protocolo Eve Lom, una limpieza facial vip con parafina caliente para facilitar la extracci\u00f3n de impurezas y aumentar la suavidad. Como broche final, un masaje drenante. La crema Madrid. Tel. 912 77 20 04, Barcel\u00f3 Sancti Petri Es perfecto para principiantes exigentes. Si no sabes cu\u00e1l es el tratamiento que mejor te va, el spa cuenta con un servicio de personal shopper beauty, sus especialistas te aconsejar\u00e1n seg\u00fan tus preferencias. La vela perfumada con tapa de metal es de Portus Cale. Urb. Loma Sancti Petri,s/n, C\u00e1diz. Tel. 956 24 27 90. Carmen Navarro \u00bfJornadas interminables? El nuevo centro de El Corte Ingl\u00e9s de Castellana te pone f\u00e1cil las citas beauty gracias a sus amplios horarios. Prueba los tratamientos con tecnolog\u00eda Bioled, que favorece la penetraci\u00f3n de los principios activos. La crema exfoliante 'Instant Body Bliss' es de Proto-col. Raimundo Fdez. Villaverde, 79, Madrid. Tel. 917 70 54 38, Asia Gardens Si lo que buscas es relajarte, este es tu lugar. Gracias a sus instalaciones acaba de ser incluido en la Leading Hotels of the World, una gu\u00eda que incluye los mejores alojamientos del mundo. Prueba su masaje Nuad Thai, de efecto equilibrante. Rotonda del Fuego, Terra M\u00edtica, Valencia. Tel. 966 81 84 00. Sha Wellness Clinic \u00bfBuscas una cura detox? Has encontrado el sitio: men\u00fas naturales, cocina macrobi\u00f3tica, yoga... Y todo esto con t\u00e9cnicas orientales mejoradas con los avances de Occidente. Prep\u00e1rate para unas vacaciones con mente y cuerpo ok. Verderol, 5, El Albir, Alicante. Tel. 966 81 11 99, Gran Hotel Bah\u00eda del Duque Spa Aseg\u00farate el buen tiempo en tus d\u00edas de descanso con una escapada a este experimentado centro. Si eres fan de los productos naturales, te encantar\u00e1n los de la firma L'Occitane. Disfruta de sus tratamientos corporales de hidrataci\u00f3n. El gel de ducha perfumado es de Bottega Veneta. Avda. de Bruselas, s/n, Costa Adeje, Tenerife. Tel. 922 74 69 00. Claudia Di Paolo Si tienes el pelo fino, castigado o sin volumen, reg\u00e1late su tratamiento a base de t\u00e9 verde J.F. Lazartigue. Un ritual que incluye una exfoliaci\u00f3n que, adem\u00e1s de mejorar el estado del cuero cabelludo, aumentar\u00e1 la luminosidad de tu melena. Jorge Juan, 39, Madrid. Tel. 915 78 26 61. Hotel Miramar \u00abUn oasis dentro de la ciudad\u00bb, as\u00ed se define el spa urbano de Alquimia. No dejes de probar el tratamiento Delicia de c\u00edtricos a base de masajes con perfumes estimulantes. Una experiencia inolvidable para los cinco sentidos. El exfoliante corporal 'Candy Scrub' de Prada, 52 \u20ac. Plaza Carlos Ib\u00e1\u00f1ez, 3, Barcelona. Tel. 932 81 16 00. Maribel Y\u00e9benes Para mejorar el aspecto de tus piernas s\u00f3lo tienes que incluir en tu wish list beauty el Tratamiento Accent. Un protocolo que te ayuda a recuperar la firmeza aumentando los niveles de col\u00e1geno y elastina. \u00bfEl resultado? Una piel mucho m\u00e1s lisa. La crema del cuerpo 'Deep Comfort' de Clinique, 37 \u20ac. Paseo de la Castellana, 114, Madrid. Tel. 914 11 74 04. La Residencia Las Islas Baleares se vuelven a posicionar en el top ten del ranking de destinos para las vacaciones. Lib\u00e9rate del estr\u00e9s con el tratamiento Citrus siesta, un lujo a base de cosm\u00e9ticos org\u00e1nicos y artesanales con efecto estimulante. Carrer dels Son Canals, s/n, Dei\u00e0, Mallorca. Tel. 971 63 90 11, Jumeirah Aqu\u00ed encontrar\u00e1s las \u00faltimas novedades en el mundo beauty. Descubre el placer sensorial de El sabor de la belleza, un protocolo que a\u00fana gastronom\u00eda y tratamientos de la mano de Natura Biss\u00e9. La mejor forma de disfrutar del verano. Carrer de B\u00e9lgica, 91, Port de S\u00f3ller, Mallorca. Tel. 971 63 78 88. Hotel Arts El mix de tratamientos naturales y vistas al mediterr\u00e1neo convierten este refugio en el lugar ideal para descansar. Prueba el Ritual tailand\u00e9s que incluye exfoliaci\u00f3n y purificaci\u00f3n de la piel y finaliza con un masaje relajante con miel y naranja. El after sun facil 'Sunle\u00ffa Soin Apr\u00e9s-Soleil' de Sisley, 158 \u20ac. Marina, 19-21,Barcelona. Tel. 932 21 10 00. BRN Concepto Es el lugar perfecto para huir de las altas temperaturas y relajarte con el Masaje de naturaleza oriental realizado con aromas de Aveda. Sus tratamientos de efecto energizante y la reflexolog\u00eda podal se adaptan a todas tus necesidades. Bail\u00e9n, 1, Sevilla. Tel. 954 56 22 55 y 954 56 22 47. \u00danico Dale el \u00faltimo empuj\u00f3n a la operaci\u00f3n biquini con unas sesiones de plataforma vibratoria. No s\u00f3lo conseguir\u00e1s mejorar el tono muscular y el riego sangu\u00edneo, tambi\u00e9n notar\u00e1s c\u00f3mo en gran medida la piel de naranja se reduce de forma visible. El after sun 'Soothing Mist Face Body' de La Prairie, 72 \u20ac. Empalme, s/n, C.C. Pe\u00f1acastillo Santander. Tel. 942 32 29 16, Mandarin oriental Antes de empezar una jornada maratoniana de compras, prepara tu piel con una dosis extra de aire con la Oxigenoterapia de Linda Meredith. La aplicaci\u00f3n del ox\u00edgeno a presi\u00f3n conseguir\u00e1 que mejore la densidad y el tono de tu piel. La crema 'Prevage Body total Transforming Moisturizer' de Elizabeth Arden, 153 \u20ac. Passeig de Gr\u00e0cia, 38-40, Barcelona. Tel. 931 51 88 88. Hospes Maricel Si llegas a la isla y eres incapazde decidirte por unsolo tratamiento date un lujo con el Bodyna capricho, que incluye exfoliaci\u00f3n con pur\u00e9 de papaya, masaje balin\u00e9s y facial, reflexolog\u00eda y aromaterapia. \u00bfQu\u00e9 m\u00e1s se puede pedir? Carretera d'Andratx, 11, Mallorca. Tel. 971 70 77 44. Hotel Es Mar\u00e8s Mezcla el lado hippie de las puestas de sol de las Baleares con el placer que se esconde tras el protocolo Diamond Magnetic Ritual, una exfoliaci\u00f3n e hidrataci\u00f3n con diamantes micronizados y gemoterapia que act\u00faa sobre los chakras. Santa Mar\u00eda, 15, Sant Francesc, Formentera. Tel. 971 32 32 16. V...Vejer Un lugar de culto para los amantes de la filosof\u00eda y tratamientos ayurv\u00e9dicos. Si vas, no te puedes perder sus masajes rejuvenecedores. \u00bfLo mejor? Si no te apetece estar en el spa, hay un servicio que ofrece tratamientos en las habitaciones. El aceite hidratante de 'Huile Prodigieuse' de Nuxe, 29,90 \u20ac. Rosario, 11-13, Vejer de la Frontera, C\u00e1diz. Tel. 956 45 17 57. El pueblo espa\u00f1ol que debes visitar en septiembre El hotel Maison Colbert es ideal para ir a Paris Guadalajara: 12 pueblos bonitos para pasar el d\u00eda El pueblo de Palencia con los mejores atardeceres "}